webpack_tools/__init__.py
webpack_tools/management/__init__.py
webpack_tools/management/commands/__init__.py
webpack_tools/management/commands/install_controller.py
webpack_tools/management/commands/stimulus.py
webpack_tools/management/commands/webpack.py
webpack_tools/migrations/__init__.py
webpack_tools/templates/webpack_tools/application.js
webpack_tools/templates/webpack_tools/controller.js
webpack_tools/templates/webpack_tools/template.html
webpack_tools/templates/webpack_tools/webpack.config.js
webpack_tools-0.2.0.dist-info/LICENSE
webpack_tools-0.2.0.dist-info/METADATA
webpack_tools-0.2.0.dist-info/WHEEL
webpack_tools-0.2.0.dist-info/top_level.txt
webpack_tools-0.2.0.dist-info/RECORD
