Metadata-Version: 2.1
Name: webpack-tools
Version: 0.2.0
Summary: Django Management Commands for using webpack (and stimulus)
Home-page: https://github.com/hotwire-django/stimulus-webpack-tools
Author: Julian Feinauer
Author-email: j.feinauer@pragmaticminds.de
License: UNKNOWN
Keywords: turbo,hotwire,stimulus,management,django
Platform: UNKNOWN
Classifier: Development Status :: 3 - Alpha
Classifier: Intended Audience :: Developers
Classifier: License :: OSI Approved :: MIT License
Classifier: Programming Language :: Python :: 3
Classifier: Programming Language :: Python :: 3.6
Classifier: Programming Language :: Python :: 3.7
Classifier: Programming Language :: Python :: 3.8
Classifier: Programming Language :: Python :: 3 :: Only
Requires-Python: >=3.6, <4
Requires-Dist: Django (>=3)
